edustats/__init__.py
edustats/google.py
edu_stats-0.1.0.dist-info/METADATA
edu_stats-0.1.0.dist-info/WHEEL
edu_stats-0.1.0.dist-info/top_level.txt
edu_stats-0.1.0.dist-info/RECORD
