Metadata-Version: 2.1
Name: edu-stats
Version: 0.1.0
Summary: Edu-Stats
Author-email: Kaveh Bakhtiyari <kbakhtiyari@yahoo.com>
Project-URL: Homepage, https://github.com/kavehbc/edu-stats
Project-URL: Bug Tracker, https://github.com/kavehbc/edu-stats
Classifier: Programming Language :: Python :: 3
Classifier: License :: OSI Approved :: MIT License
Classifier: Operating System :: OS Independent
Requires-Python: >=3.8
